__init__.py
main.py
container_health_exporter-0.1.1.dist-info/LICENSE.md
container_health_exporter-0.1.1.dist-info/METADATA
container_health_exporter-0.1.1.dist-info/WHEEL
container_health_exporter-0.1.1.dist-info/entry_points.txt
container_health_exporter-0.1.1.dist-info/top_level.txt
container_health_exporter-0.1.1.dist-info/RECORD
