Metadata-Version: 2.1
Name: container_health_exporter
Version: 0.1.1
Summary: Package, package, package
Author-email: Ilya Vassyutovich <me@iv.link>
Project-URL: Homepage, https://github.com/TBD
Project-URL: Issues, https://github.com/TBD
Classifier: Programming Language :: Python :: 3
Classifier: License :: OSI Approved :: MIT License
Classifier: Operating System :: POSIX :: Linux
Requires-Python: >=3.10
License-File: LICENSE.md
Requires-Dist: docker <8,>=7.1.0
Requires-Dist: prometheus-client <0.21,>=0.20
